payments/__init__.py
payments/admin.py
payments/forms.py
payments/managers.py
payments/middleware.py
payments/models.py
payments/settings.py
payments/signals.py
payments/utils.py
payments/api/__init__.py
payments/api/abstract.py
payments/api/serializers.py
payments/api/urls.py
payments/api/views.py
payments/management/__init__.py
payments/management/commands/__init__.py
payments/management/commands/init_customers.py
payments/management/commands/init_plans.py
payments/management/commands/sync_customers.py
payments/migrations/0001_initial.py
payments/migrations/0002_auto_20220523_0901.py
payments/migrations/__init__.py
payments/templatetags/__init__.py
payments/templatetags/payments_tags.py
payments/tests/__init__.py
payments/tests/callbacks.py
payments/tests/mock_views.py
payments/tests/test_commands.py
payments/tests/test_customer.py
payments/tests/test_email.py
payments/tests/test_event.py
payments/tests/test_managers.py
payments/tests/test_middleware.py
payments/tests/test_templatetags.py
payments/tests/test_urls.py
payments/tests/test_utils.py
payments/tests/test_views.py
payments/tests/test_webhooks.py
drf_stripe-1.2.6.dist-info/AUTHORS
drf_stripe-1.2.6.dist-info/LICENSE
drf_stripe-1.2.6.dist-info/METADATA
drf_stripe-1.2.6.dist-info/WHEEL
drf_stripe-1.2.6.dist-info/top_level.txt
drf_stripe-1.2.6.dist-info/RECORD
