Metadata-Version: 2.1
Name: drf-stripe
Version: 1.2.6
Summary: Django REST Framework wrapper of the payments Django app for Stripe
Home-page: https://github.com/null-none/drf-stripe
Author: Kalinin Mitko
Author-email: kalinin.mitko@gmail.com
License: MIT
Classifier: Development Status :: 3 - Alpha
Classifier: Environment :: Web Environment
Classifier: Intended Audience :: Developers
Classifier: License :: OSI Approved :: BSD License
Classifier: Operating System :: OS Independent
Classifier: Programming Language :: Python
Classifier: Programming Language :: Python :: 2
Classifier: Programming Language :: Python :: 3
Classifier: Framework :: Django
License-File: LICENSE
License-File: AUTHORS
Requires-Dist: stripe (>=1.7.9)
Requires-Dist: django (>=1.6)
Requires-Dist: pytz
Requires-Dist: six
Requires-Dist: djangorestframework (>=3.1.1)
Requires-Dist: jsonfield (>=1.0.3)
